tensorflow_deploy_utils/TFD.py
tensorflow_deploy_utils/__init__.py
tensorflow_deploy_utils/version.py
tensorflow_deploy_utils/scripts/__init__.py
tensorflow_deploy_utils/scripts/create_archive.py
tensorflow_deploy_utils/scripts/delete_label.py
tensorflow_deploy_utils/scripts/delete_model.py
tensorflow_deploy_utils/scripts/delete_module.py
tensorflow_deploy_utils/scripts/deploy_model.py
tensorflow_deploy_utils/scripts/get_config.py
tensorflow_deploy_utils/scripts/get_model.py
tensorflow_deploy_utils/scripts/get_module.py
tensorflow_deploy_utils/scripts/list_models.py
tensorflow_deploy_utils/scripts/list_modules.py
tensorflow_deploy_utils/scripts/reload_config.py
tensorflow_deploy_utils/scripts/revert_model.py
tensorflow_deploy_utils/scripts/set_label.py
tensorflow_deploy_utils/scripts/set_stable.py
tensorflow_deploy_utils/scripts/upload_model.py
tensorflow_deploy_utils/scripts/upload_module.py
test/__init__.py
test/test_TFD.py
tensorflow_deploy_utils-1.0.0.dist-info/LICENSE
tensorflow_deploy_utils-1.0.0.dist-info/METADATA
tensorflow_deploy_utils-1.0.0.dist-info/WHEEL
tensorflow_deploy_utils-1.0.0.dist-info/entry_points.txt
tensorflow_deploy_utils-1.0.0.dist-info/top_level.txt
tensorflow_deploy_utils-1.0.0.dist-info/RECORD
