Metadata-Version: 2.1
Name: tensorflow-deploy-utils
Version: 1.0.0
Summary: Utils for managing and communication with TensorFlow Deploy
Home-page: https://github.com/grupawp/tensorflow-deploy-utils
Author: Wirtualna Polska Media S.A.
Author-email: tfd@grupawp.pl
License: ISC
Project-URL: Documentation, https://github.com/grupawp/tensorflow-deploy-utils
Project-URL: Source, https://github.com/grupawp/tensorflow-deploy-utils
Project-URL: Bug Report, https://github.com/grupawp/tensorflow-deploy-utils/issues
Keywords: tensorflow ai ml machine learning production serving kubernetes deploy tf tfd tfs
Platform: UNKNOWN
Classifier: Programming Language :: Python :: 3
Classifier: License :: OSI Approved :: ISC License (ISCL)
Classifier: Operating System :: OS Independent
Requires-Python: >=3.6
Requires-Dist: pandas
Requires-Dist: requests
Requires-Dist: tensorflow
Requires-Dist: tensorflow-text
Requires-Dist: requests-mock
Requires-Dist: coverage
